wheelsmith/__init__.py
wheelsmith/__main__.py
wheelsmith/wheelsmith.py
wheelsmith-0.1.1.dist-info/METADATA
wheelsmith-0.1.1.dist-info/WHEEL
wheelsmith-0.1.1.dist-info/entry_points.txt
wheelsmith-0.1.1.dist-info/top_level.txt
wheelsmith-0.1.1.dist-info/RECORD
