Metadata-Version: 2.1
Name: wheelsmith
Version: 0.1.1
Summary: A utility tool for building and publishing Python packages to PyPI
Home-page: UNKNOWN
Author: Your Name
Author-email: your.email@example.com
License: UNKNOWN
Keywords: python,packaging,pypi,wheels,publishing
Platform: UNKNOWN
Classifier: Development Status :: 4 - Beta
Classifier: Intended Audience :: Developers
Classifier: Programming Language :: Python :: 3
Classifier: Operating System :: Unix
Classifier: Operating System :: MacOS :: MacOS X
Classifier: Operating System :: Microsoft :: Windows
Requires-Dist: wheel
Requires-Dist: twine
Requires-Dist: rich
